fic_evaluation/__init__.py
fic_evaluation/src/__init__.py
fic_evaluation/src/highlights_coverage_evaluator.py
fic_evaluation/src/highlights_faithfulness_evaluator.py
fic_evaluation-0.1.0.dist-info/LICENSE
fic_evaluation-0.1.0.dist-info/METADATA
fic_evaluation-0.1.0.dist-info/WHEEL
fic_evaluation-0.1.0.dist-info/top_level.txt
fic_evaluation-0.1.0.dist-info/RECORD
